jgdv/__init__.py
jgdv/py.typed
jgdv/__tests/__init__.py
jgdv/__tests/test_low_level.py
jgdv/_abstract/__init__.py
jgdv/_abstract/error.py
jgdv/_abstract/index.rst
jgdv/_abstract/prelude.py
jgdv/_abstract/typeguards.py
jgdv/_abstract/types.py
jgdv/_abstract/__tests/__init__.py
jgdv/_abstract/__tests/test_error.py
jgdv/_abstract/protocols/__init__.py
jgdv/_abstract/protocols/general.py
jgdv/_abstract/protocols/pre_processable.py
jgdv/_abstract/protocols/pydantic.py
jgdv/_abstract/protocols/stdlib.py
jgdv/_abstract/protocols/str.py
jgdv/cli/__init__.py
jgdv/cli/_interface.py
jgdv/cli/builder_mixin.py
jgdv/cli/errors.py
jgdv/cli/parse_machine.py
jgdv/cli/parser_model.py
jgdv/cli/__tests/__init__.py
jgdv/cli/__tests/test_builder_mixin.py
jgdv/cli/__tests/test_parse_machine.py
jgdv/cli/__tests/test_parser_model.py
jgdv/cli/_graphs/_ParseMachine.dot
jgdv/cli/param_spec/__init__.py
jgdv/cli/param_spec/core.py
jgdv/cli/param_spec/defaults.py
jgdv/cli/param_spec/extra.py
jgdv/cli/param_spec/param_spec.py
jgdv/cli/param_spec/__tests/__init__.py
jgdv/cli/param_spec/__tests/test_core.py
jgdv/cli/param_spec/__tests/test_defaults.py
jgdv/cli/param_spec/__tests/test_extra.py
jgdv/cli/param_spec/__tests/test_param_spec.py
jgdv/debugging/__init__.py
jgdv/debugging/_interface.py
jgdv/debugging/destruction.py
jgdv/debugging/dsl.py
jgdv/debugging/index.rst
jgdv/debugging/malloc_tool.py
jgdv/debugging/running_debugger.py
jgdv/debugging/signal_handler.py
jgdv/debugging/timing.py
jgdv/debugging/trace_context.py
jgdv/debugging/traceback_factory.py
jgdv/debugging/__tests/__init__.py
jgdv/debugging/__tests/basic.cache
jgdv/debugging/__tests/test_malloc_tool.py
jgdv/debugging/__tests/test_timing.py
jgdv/debugging/__tests/test_trace_context.coverage
jgdv/debugging/__tests/test_trace_context.py
jgdv/debugging/__tests/test_traceback_factory.py
jgdv/debugging/__tests/trace.cache
jgdv/debugging/__tests/coverage_flat/test_trace_context.coverage
jgdv-1.3.2.dist-info/licenses/LICENSE
jgdv-1.3.2.dist-info/METADATA
jgdv-1.3.2.dist-info/WHEEL
jgdv-1.3.2.dist-info/top_level.txt
jgdv-1.3.2.dist-info/RECORD
