Metadata-Version: 2.4
Name: jgdv
Version: 1.3.2
Summary: I Keep Writing These Things.
Author-email: John Grey <jgrey.n.plus.one+jgdv@gmail.com>
Project-URL: homepage, https://github.com/jgrey4296/jgdv
Project-URL: documentation, https://jgdv.readthedocs.io/en/latest
Project-URL: repository, https://github.com/jgrey4296/jgdv
Project-URL: changelog, https://github.com/jgrey4296/jgdv/blob/master/CHANGELOG.md
Keywords: utility,strang,toml
Classifier: Programming Language :: Python
Requires-Python: >=3.12
License-File: LICENSE
Requires-Dist: pyparsing
Requires-Dist: networkx
Requires-Dist: pydantic>=2.9.0
Requires-Dist: python-statemachine>=2.5.0
Requires-Dist: sh>=2.1.0
Requires-Dist: stackprinter>=0.2.0
Requires-Dist: sty>=1.0.6
Requires-Dist: packaging>=24.2
Dynamic: license-file
